{
    "course_id": "MUS_29360",
    "sql_id": "104174663",
    "course_name": "爵士理論與即興 (二)",
    "english_course_name": "Jazz Musicianship(Ⅱ)",
    "credits": "2/2",
    "teacher": [
        "許郁瑛"
    ],
    "classroom": [
        "學生活動中心B129",
        "學生活動中心B129"
    ],
    "class_time": [
        {
            "day": "二",
            "period": "10"
        },
        {
            "day": "二",
            "period": "11"
        }
    ],
    "syllabus_link": "https://sys.ndhu.edu.tw/AA/CLASS/SOutLine/OutLineForm.aspx?rid=104174663",
    "teaching_plan_link": "https://sys.ndhu.edu.tw/AA/CLASS/TeacherSubj/prt_tplan.aspx?no=104174663",
    "departments": [
        {
            "college": "藝術學院::COLLEGE OF THE ARTS",
            "department": "音樂學系::DEPARTMENT OF MUSIC"
        }
    ]
}