{
    "course_id": "CE__4010AB",
    "sql_id": "110130872",
    "course_name": "教育社會學AB",
    "english_course_name": "Sociology of Education",
    "credits": "2/2",
    "teacher": [
        "高建民"
    ],
    "classroom": [
        "教育學院C223",
        "教育學院C223"
    ],
    "class_time": [
        {
            "day": "三",
            "period": "11"
        },
        {
            "day": "三",
            "period": "12"
        }
    ],
    "syllabus_link": "https://sys.ndhu.edu.tw/AA/CLASS/SOutLine/OutLineForm.aspx?rid=110130872",
    "teaching_plan_link": "https://sys.ndhu.edu.tw/AA/CLASS/TeacherSubj/prt_tplan.aspx?no=110130872",
    "departments": [
        {
            "college": "花師教育學院::HUA-SHIH COLLEGE OF EDUCATION",
            "department": "花師教育學院學士班::BACHELOR"
        },
        {
            "college": "花師教育學院::HUA-SHIH COLLEGE OF EDUCATION",
            "department": "教育行政與管理學系::DEPARTMENT OF EDUCATIONAL ADMINISTRATION AND MANAGEMENT"
        }
    ]
}