{
    "course_id": "ECE_32640",
    "sql_id": "114178305",
    "course_name": "幼兒園課室經營",
    "english_course_name": "Classroom Management in Preschool",
    "credits": "2/2",
    "teacher": [
        "張凱程"
    ],
    "classroom": [
        "教育學院B126",
        "教育學院B126"
    ],
    "class_time": [
        {
            "day": "二",
            "period": "8"
        },
        {
            "day": "二",
            "period": "9"
        }
    ],
    "syllabus_link": "https://sys.ndhu.edu.tw/AA/CLASS/SOutLine/OutLineForm.aspx?rid=114178305",
    "teaching_plan_link": "https://sys.ndhu.edu.tw/AA/CLASS/TeacherSubj/prt_tplan.aspx?no=114178305",
    "departments": [
        {
            "college": "花師教育學院::HUA-SHIH COLLEGE OF EDUCATION",
            "department": "幼兒教育學系::DEPARTMENT OF EARLY CHILDHOOD EDUCATION"
        }
    ]
}