{
    "course_id": "MUS_5230AA",
    "sql_id": "109224033",
    "course_name": "鋼琴（二）AA",
    "english_course_name": "Piano(II)",
    "credits": "1/1",
    "teacher": [
        "于汶蕙"
    ],
    "classroom": [
        "教師研究室"
    ],
    "class_time": [
        {
            "day": "五",
            "period": "1"
        }
    ],
    "syllabus_link": "https://sys.ndhu.edu.tw/AA/CLASS/SOutLine/OutLineForm.aspx?rid=109224033",
    "teaching_plan_link": "https://sys.ndhu.edu.tw/AA/CLASS/TeacherSubj/prt_tplan.aspx?no=109224033",
    "departments": [
        {
            "college": "藝術學院::COLLEGE OF THE ARTS",
            "department": "音樂學系::DEPARTMENT OF MUSIC"
        }
    ]
}