{
    "course_id": "PA__30020",
    "sql_id": "105133644",
    "course_name": "財務行政",
    "english_course_name": "Fiscal Administration",
    "credits": "2/2",
    "teacher": [
        "魯炳炎"
    ],
    "classroom": [
        "人社一館B203",
        "人社一館B203"
    ],
    "class_time": [
        {
            "day": "五",
            "period": "8"
        },
        {
            "day": "五",
            "period": "9"
        }
    ],
    "syllabus_link": "https://sys.ndhu.edu.tw/AA/CLASS/SOutLine/OutLineForm.aspx?rid=105133644",
    "teaching_plan_link": "https://sys.ndhu.edu.tw/AA/CLASS/TeacherSubj/prt_tplan.aspx?no=105133644",
    "departments": [
        {
            "college": "人文社會科學學院::COLLEGE OF HUMANITIES AND SOCIAL SCIENCES",
            "department": "公共行政學系::DEPARTMENT OF PUBLIC ADMINISTRATION"
        }
    ]
}