{
    "course_id": "TRLS52030",
    "sql_id": "103117275",
    "course_name": "專題講座(二)",
    "english_course_name": "Special Topics in Seminar (II)",
    "credits": "1/2",
    "teacher": [
        "謝奇明"
    ],
    "classroom": [
        "管D211",
        "管D211"
    ],
    "class_time": [
        {
            "day": "一",
            "period": "11"
        },
        {
            "day": "一",
            "period": "12"
        }
    ],
    "syllabus_link": "https://sys.ndhu.edu.tw/AA/CLASS/SOutLine/OutLineForm.aspx?rid=103117275",
    "teaching_plan_link": "https://sys.ndhu.edu.tw/AA/CLASS/TeacherSubj/prt_tplan.aspx?no=103117275",
    "departments": [
        {
            "college": "管理學院::COLLEGE OF MANAGEMENT",
            "department": "觀光暨休閒遊憩學系::DEPARTMENT OF TOURISM, RECREATION AND LEISURE STUDIES"
        }
    ]
}