{
    "course_id": "AD__4210AB",
    "sql_id": "103273756",
    "course_name": "專題製作(二)AB",
    "english_course_name": "Special Topics (II)",
    "credits": "1/1",
    "teacher": [
        "黃琡雅",
        "韓毓琦"
    ],
    "classroom": [
        "藝坊109"
    ],
    "class_time": [
        {
            "day": "一",
            "period": "4"
        }
    ],
    "syllabus_link": "https://sys.ndhu.edu.tw/AA/CLASS/SOutLine/OutLineForm.aspx?rid=103273756",
    "teaching_plan_link": "https://sys.ndhu.edu.tw/AA/CLASS/TeacherSubj/prt_tplan.aspx?no=103273756",
    "departments": [
        {
            "college": "藝術學院::COLLEGE OF THE ARTS",
            "department": "藝術與設計學系::DEPARTMENT OF ARTS AND DESIGN"
        }
    ]
}