{
    "course_id": "GC__12100",
    "sql_id": "103223673",
    "course_name": "藥物濫用防制",
    "english_course_name": "Prevention against Drug Abuse",
    "credits": "2/2",
    "teacher": [
        "劉振倫"
    ],
    "classroom": [
        "管二講堂D124",
        "管二講堂D124"
    ],
    "class_time": [
        {
            "day": "二",
            "period": "5"
        },
        {
            "day": "二",
            "period": "6"
        }
    ],
    "syllabus_link": "https://sys.ndhu.edu.tw/AA/CLASS/SOutLine/OutLineForm.aspx?rid=103223673",
    "teaching_plan_link": "https://sys.ndhu.edu.tw/AA/CLASS/TeacherSubj/prt_tplan.aspx?no=103223673",
    "departments": [
        {
            "college": "通識教育中心::GENERAL EDUCATION CENTER",
            "department": "通識教育中心學士班::BACHELOR"
        }
    ]
}