{
    "course_id": "TS__5002Z",
    "sql_id": "105195061",
    "course_name": "臺灣鄉土文學研究",
    "english_course_name": "Studies on Local Literature of Taiwan",
    "credits": "3/3",
    "teacher": [
        "郭澤寬"
    ],
    "classroom": [
        "人社一館B206",
        "人社一館B206",
        "人社一館B206",
        "人社一館B206",
        "人社一館B206",
        "人社一館B206"
    ],
    "class_time": [
        {
            "day": "六",
            "period": "4"
        },
        {
            "day": "六",
            "period": "5"
        },
        {
            "day": "六",
            "period": "6"
        },
        {
            "day": "六",
            "period": "9"
        },
        {
            "day": "六",
            "period": "10"
        },
        {
            "day": "六",
            "period": "11"
        }
    ],
    "syllabus_link": "https://sys.ndhu.edu.tw/AA/CLASS/SOutLine/OutLineForm.aspx?rid=105195061",
    "teaching_plan_link": "https://sys.ndhu.edu.tw/AA/CLASS/TeacherSubj/prt_tplan.aspx?no=105195061",
    "departments": [
        {
            "college": "人文社會科學學院::COLLEGE OF HUMANITIES AND SOCIAL SCIENCES",
            "department": "臺灣文化學系::DEPARTMENT OF TAIWAN AND REGIONAL STUDIES"
        }
    ]
}