{
    "course_id": "SCE_71930",
    "sql_id": "107299868",
    "course_name": "語言與科學學習特論",
    "english_course_name": "Advanced Issues in Language and Science Learning",
    "credits": "3/3",
    "teacher": [
        "蓋允萍"
    ],
    "classroom": [
        "教育學院B329",
        "教育學院B329",
        "教育學院B329"
    ],
    "class_time": [
        {
            "day": "四",
            "period": "4"
        },
        {
            "day": "四",
            "period": "5"
        },
        {
            "day": "四",
            "period": "6"
        }
    ],
    "syllabus_link": "https://sys.ndhu.edu.tw/AA/CLASS/SOutLine/OutLineForm.aspx?rid=107299868",
    "teaching_plan_link": "https://sys.ndhu.edu.tw/AA/CLASS/TeacherSubj/prt_tplan.aspx?no=107299868",
    "departments": [
        {
            "college": "花師教育學院::HUA-SHIH COLLEGE OF EDUCATION",
            "department": "教育與潛能開發學系::DEPARTMENT OF EDUCATION AND HUMAN POTENTIALS DEVELOPMENT"
        }
    ]
}