{
    "course_id": "UPOL10220",
    "sql_id": "107210710",
    "course_name": "行政法總論",
    "english_course_name": "General Theory on Administrative Law",
    "credits": "3/3",
    "teacher": [
        "賴宇松"
    ],
    "classroom": [
        "人社二館B107",
        "人社二館B107",
        "人社二館B107"
    ],
    "class_time": [
        {
            "day": "三",
            "period": "4"
        },
        {
            "day": "三",
            "period": "5"
        },
        {
            "day": "三",
            "period": "6"
        }
    ],
    "syllabus_link": "https://sys.ndhu.edu.tw/AA/CLASS/SOutLine/OutLineForm.aspx?rid=107210710",
    "teaching_plan_link": "https://sys.ndhu.edu.tw/AA/CLASS/TeacherSubj/prt_tplan.aspx?no=107210710",
    "departments": [
        {
            "college": "人文社會科學學院::COLLEGE OF HUMANITIES AND SOCIAL SCIENCES",
            "department": "法律學士學位學程::UNDERGRADUATE PROGRAM OF LAW"
        },
        {
            "college": "人文社會科學學院::COLLEGE OF HUMANITIES AND SOCIAL SCIENCES",
            "department": "法律學士學位學程原住民專班::UNDERGRADUATE PROGRAM OF LAW(INDIGENOUS LAW PROGRAM)"
        }
    ]
}