{
    "course_id": "GC__3970AB",
    "sql_id": "108190740",
    "course_name": "素材應用與空間美學AB",
    "english_course_name": "Source Material Utilization and Spatial Esthetics",
    "credits": "2/2",
    "teacher": [
        "蔡文慶"
    ],
    "classroom": [
        "人社三館D103",
        "人社三館D103"
    ],
    "class_time": [
        {
            "day": "四",
            "period": "12"
        },
        {
            "day": "四",
            "period": "13"
        }
    ],
    "syllabus_link": "https://sys.ndhu.edu.tw/AA/CLASS/SOutLine/OutLineForm.aspx?rid=108190740",
    "teaching_plan_link": "https://sys.ndhu.edu.tw/AA/CLASS/TeacherSubj/prt_tplan.aspx?no=108190740",
    "departments": [
        {
            "college": "通識教育中心::GENERAL EDUCATION CENTER",
            "department": "通識教育中心學士班::BACHELOR"
        }
    ]
}