{
    "course_id": "MUS_53200",
    "sql_id": "107178410",
    "course_name": "指揮法研究",
    "english_course_name": "Seminar in Conducting",
    "credits": "2/2",
    "teacher": [
        "彭翠萍"
    ],
    "classroom": [
        "學生活動中心B102",
        "學生活動中心B102"
    ],
    "class_time": [
        {
            "day": "一",
            "period": "13"
        },
        {
            "day": "一",
            "period": "14"
        }
    ],
    "syllabus_link": "https://sys.ndhu.edu.tw/AA/CLASS/SOutLine/OutLineForm.aspx?rid=107178410",
    "teaching_plan_link": "https://sys.ndhu.edu.tw/AA/CLASS/TeacherSubj/prt_tplan.aspx?no=107178410",
    "departments": [
        {
            "college": "藝術學院::COLLEGE OF THE ARTS",
            "department": "音樂學系::DEPARTMENT OF MUSIC"
        }
    ]
}