{
    "course_id": "IM__41780",
    "sql_id": "109101070",
    "course_name": "「一支麥克風」駐校記者培育計畫",
    "english_course_name": "University Correspondent Development Program",
    "credits": "2/2",
    "teacher": [
        "葉國暉",
        "林俞君",
        "游璟蓉"
    ],
    "classroom": [
        "管理學院D117",
        "管理學院D117"
    ],
    "class_time": [
        {
            "day": "三",
            "period": "9"
        },
        {
            "day": "三",
            "period": "10"
        }
    ],
    "syllabus_link": "https://sys.ndhu.edu.tw/AA/CLASS/SOutLine/OutLineForm.aspx?rid=109101070",
    "teaching_plan_link": "https://sys.ndhu.edu.tw/AA/CLASS/TeacherSubj/prt_tplan.aspx?no=109101070",
    "departments": [
        {
            "college": "管理學院::COLLEGE OF MANAGEMENT",
            "department": "資訊管理學系::DEPARTMENT OF INFORMATION MANAGEMENT"
        }
    ]
}