{
    "course_id": "BM__5390AF",
    "sql_id": "108178378",
    "course_name": "專題研究AF",
    "english_course_name": "Independent Study",
    "credits": "3/3",
    "teacher": [
        "蕭朝興"
    ],
    "classroom": [
        "研究室",
        "研究室",
        "研究室"
    ],
    "class_time": [
        {
            "day": "六",
            "period": "1"
        },
        {
            "day": "六",
            "period": "2"
        },
        {
            "day": "六",
            "period": "3"
        }
    ],
    "syllabus_link": "https://sys.ndhu.edu.tw/AA/CLASS/SOutLine/OutLineForm.aspx?rid=108178378",
    "teaching_plan_link": "https://sys.ndhu.edu.tw/AA/CLASS/TeacherSubj/prt_tplan.aspx?no=108178378",
    "departments": [
        {
            "college": "管理學院::COLLEGE OF MANAGEMENT",
            "department": "企業管理學系::DEPARTMENT OF BUSINESS ADMINISTRATION"
        }
    ]
}