{
    "course_id": "CDPD22410",
    "sql_id": "110104348",
    "course_name": "教學媒體與運用",
    "english_course_name": "Instructional Media and Application",
    "credits": "2/2",
    "teacher": [
        "高台茜"
    ],
    "classroom": [
        "教育學院B309",
        "教育學院B309"
    ],
    "class_time": [
        {
            "day": "一",
            "period": "8"
        },
        {
            "day": "一",
            "period": "9"
        }
    ],
    "syllabus_link": "https://sys.ndhu.edu.tw/AA/CLASS/SOutLine/OutLineForm.aspx?rid=110104348",
    "teaching_plan_link": "https://sys.ndhu.edu.tw/AA/CLASS/TeacherSubj/prt_tplan.aspx?no=110104348",
    "departments": [
        {
            "college": "花師教育學院::HUA-SHIH COLLEGE OF EDUCATION",
            "department": "教育與潛能開發學系::DEPARTMENT OF EDUCATION AND HUMAN POTENTIALS DEVELOPMENT"
        }
    ]
}