{
    "course_id": "SCE_51800",
    "sql_id": "113245675",
    "course_name": "物理特論",
    "english_course_name": "Special Topics in Physics",
    "credits": "3/3",
    "teacher": [
        "陳世文"
    ],
    "classroom": [
        "教育學院D325",
        "教育學院D325",
        "教育學院D325"
    ],
    "class_time": [
        {
            "day": "五",
            "period": "7"
        },
        {
            "day": "五",
            "period": "8"
        },
        {
            "day": "五",
            "period": "9"
        }
    ],
    "syllabus_link": "https://sys.ndhu.edu.tw/AA/CLASS/SOutLine/OutLineForm.aspx?rid=113245675",
    "teaching_plan_link": "https://sys.ndhu.edu.tw/AA/CLASS/TeacherSubj/prt_tplan.aspx?no=113245675",
    "departments": [
        {
            "college": "花師教育學院::HUA-SHIH COLLEGE OF EDUCATION",
            "department": "教育與潛能開發學系::DEPARTMENT OF EDUCATION AND HUMAN POTENTIALS DEVELOPMENT"
        }
    ]
}