{
    "course_id": "YY__1010BA",
    "sql_id": "113294788",
    "course_name": "體育(二)BA",
    "english_course_name": "Physical Education (II)",
    "credits": "1/2",
    "teacher": [
        "陳孝夫"
    ],
    "classroom": [
        "D區桌球室",
        "D區體能訓練室",
        "D區桌球室",
        "D區體能訓練室"
    ],
    "class_time": [
        {
            "day": "四",
            "period": "11"
        },
        {
            "day": "四",
            "period": "12"
        }
    ],
    "syllabus_link": "https://sys.ndhu.edu.tw/AA/CLASS/SOutLine/OutLineForm.aspx?rid=113294788",
    "teaching_plan_link": "https://sys.ndhu.edu.tw/AA/CLASS/TeacherSubj/prt_tplan.aspx?no=113294788",
    "departments": [
        {
            "college": "藝術學院::COLLEGE OF THE ARTS",
            "department": "藝術與設計學系::DEPARTMENT OF ARTS AND DESIGN"
        },
        {
            "college": "洄瀾學院::COLLEGE OF HUILAN",
            "department": "體育中心::PHYSICAL EDUCATION CENTER"
        },
        {
            "college": "校核心課程::University Core Curriculum",
            "department": "校核心課程::University Core Curriculum"
        },
        {
            "college": "校核心課程::University Core Curriculum",
            "department": "體育課程::Physical education courses"
        }
    ]
}