{
    "course_id": "BM__63500",
    "sql_id": "105190029",
    "course_name": "專題討論：企業專題講座(一)",
    "english_course_name": "Seminar in Business Management Practice (Ⅰ)",
    "credits": "0/1",
    "teacher": [
        "林家五",
        "祝道松",
        "溫日華"
    ],
    "classroom": [
        "教育學院-階梯教室(一)C128"
    ],
    "class_time": [
        {
            "day": "五",
            "period": "9"
        }
    ],
    "syllabus_link": "https://sys.ndhu.edu.tw/AA/CLASS/SOutLine/OutLineForm.aspx?rid=105190029",
    "teaching_plan_link": "https://sys.ndhu.edu.tw/AA/CLASS/TeacherSubj/prt_tplan.aspx?no=105190029",
    "departments": [
        {
            "college": "管理學院::COLLEGE OF MANAGEMENT",
            "department": "企業管理學系::DEPARTMENT OF BUSINESS ADMINISTRATION"
        }
    ]
}