{
    "course_id": "SPE_31190",
    "sql_id": "109288518",
    "course_name": "重度與多重障礙",
    "english_course_name": "Severe and Profound Disabilities",
    "credits": "2/2",
    "teacher": [
        "黃榮真"
    ],
    "classroom": [
        "教育學院C131",
        "教育學院C131"
    ],
    "class_time": [
        {
            "day": "五",
            "period": "3"
        },
        {
            "day": "五",
            "period": "4"
        }
    ],
    "syllabus_link": "https://sys.ndhu.edu.tw/AA/CLASS/SOutLine/OutLineForm.aspx?rid=109288518",
    "teaching_plan_link": "https://sys.ndhu.edu.tw/AA/CLASS/TeacherSubj/prt_tplan.aspx?no=109288518",
    "departments": [
        {
            "college": "花師教育學院::HUA-SHIH COLLEGE OF EDUCATION",
            "department": "特殊教育學系::DEPARTMENT OF SPECIAL EDUCATION"
        }
    ]
}