{
    "course_id": "BM__7340AA",
    "sql_id": "100260396",
    "course_name": "專題研究(一)AA",
    "english_course_name": "Special Topic for Research (I)",
    "credits": "1/1",
    "teacher": [
        "楊維邦",
        "蔡裕源"
    ],
    "classroom": [
        "研究室"
    ],
    "class_time": [
        {
            "day": "六",
            "period": "2"
        }
    ],
    "syllabus_link": "https://sys.ndhu.edu.tw/AA/CLASS/SOutLine/OutLineForm.aspx?rid=100260396",
    "teaching_plan_link": "https://sys.ndhu.edu.tw/AA/CLASS/TeacherSubj/prt_tplan.aspx?no=100260396",
    "departments": [
        {
            "college": "管理學院::COLLEGE OF MANAGEMENT",
            "department": "企業管理學系::DEPARTMENT OF BUSINESS ADMINISTRATION"
        }
    ]
}