{
    "course_id": "CLL_22040",
    "sql_id": "100235126",
    "course_name": "李白詩",
    "english_course_name": "Li Bai's Poems",
    "credits": "3/3",
    "teacher": [
        "劉漢初"
    ],
    "classroom": [
        "文B105",
        "文B105",
        "文B105"
    ],
    "class_time": [
        {
            "day": "一",
            "period": "11"
        },
        {
            "day": "一",
            "period": "12"
        },
        {
            "day": "一",
            "period": "13"
        }
    ],
    "syllabus_link": "https://sys.ndhu.edu.tw/AA/CLASS/SOutLine/OutLineForm.aspx?rid=100235126",
    "teaching_plan_link": "https://sys.ndhu.edu.tw/AA/CLASS/TeacherSubj/prt_tplan.aspx?no=100235126",
    "departments": [
        {
            "college": "人文社會科學學院::COLLEGE OF HUMANITIES AND SOCIAL SCIENCES",
            "department": "中國語文學系::DEPARTMENT OF CHINESE LANGUAGE AND LITERATURE"
        }
    ]
}