{
    "course_id": "IM__21400",
    "sql_id": "100242735",
    "course_name": "多媒體導論",
    "english_course_name": "Introduction to Multimedia",
    "credits": "3/3",
    "teacher": [
        "葉國暉"
    ],
    "classroom": [
        "ERP教室",
        "ERP教室",
        "ERP教室"
    ],
    "class_time": [
        {
            "day": "五",
            "period": "4"
        },
        {
            "day": "五",
            "period": "5"
        },
        {
            "day": "五",
            "period": "6"
        }
    ],
    "syllabus_link": "https://sys.ndhu.edu.tw/AA/CLASS/SOutLine/OutLineForm.aspx?rid=100242735",
    "teaching_plan_link": "https://sys.ndhu.edu.tw/AA/CLASS/TeacherSubj/prt_tplan.aspx?no=100242735",
    "departments": [
        {
            "college": "管理學院::COLLEGE OF MANAGEMENT",
            "department": "資訊管理學系::DEPARTMENT OF INFORMATION MANAGEMENT"
        }
    ]
}