{
    "course_id": "GC__62670",
    "sql_id": "101187752",
    "course_name": "英國文化",
    "english_course_name": "UK Culture",
    "credits": "2/2",
    "teacher": [
        "李佩容"
    ],
    "classroom": [
        "民A201",
        "民A201"
    ],
    "class_time": [
        {
            "day": "三",
            "period": "5"
        },
        {
            "day": "三",
            "period": "6"
        }
    ],
    "syllabus_link": "https://sys.ndhu.edu.tw/AA/CLASS/SOutLine/OutLineForm.aspx?rid=101187752",
    "teaching_plan_link": "https://sys.ndhu.edu.tw/AA/CLASS/TeacherSubj/prt_tplan.aspx?no=101187752",
    "departments": [
        {
            "college": "通識教育中心::GENERAL EDUCATION CENTER",
            "department": "通識教育中心學士班::BACHELOR"
        }
    ]
}