{
    "course_id": "CE__3051AA",
    "sql_id": "111181667",
    "course_name": "教學原理AA",
    "english_course_name": "Theory and Practice of Teaching Principles of Instruction",
    "credits": "2/2",
    "teacher": [
        "黃玉如"
    ],
    "classroom": [
        "教育學院B124",
        "教育學院B124"
    ],
    "class_time": [
        {
            "day": "三",
            "period": "5"
        },
        {
            "day": "三",
            "period": "6"
        }
    ],
    "syllabus_link": "https://sys.ndhu.edu.tw/AA/CLASS/SOutLine/OutLineForm.aspx?rid=111181667",
    "teaching_plan_link": "https://sys.ndhu.edu.tw/AA/CLASS/TeacherSubj/prt_tplan.aspx?no=111181667",
    "departments": [
        {
            "college": "花師教育學院::HUA-SHIH COLLEGE OF EDUCATION",
            "department": "花師教育學院學士班::BACHELOR"
        },
        {
            "college": "花師教育學院::HUA-SHIH COLLEGE OF EDUCATION",
            "department": "教育行政與管理學系::DEPARTMENT OF EDUCATIONAL ADMINISTRATION AND MANAGEMENT"
        }
    ]
}