{
    "course_id": "GC__6232AF",
    "sql_id": "111185018",
    "course_name": "中文能力與涵養AF",
    "english_course_name": "Chinese language ability and education",
    "credits": "3/3",
    "teacher": [
        "顏進雄"
    ],
    "classroom": [
        "人社二館-第二講堂B007",
        "人社二館-第二講堂B007",
        "人社二館-第二講堂B007"
    ],
    "class_time": [
        {
            "day": "一",
            "period": "4"
        },
        {
            "day": "一",
            "period": "5"
        },
        {
            "day": "一",
            "period": "6"
        }
    ],
    "syllabus_link": "https://sys.ndhu.edu.tw/AA/CLASS/SOutLine/OutLineForm.aspx?rid=111185018",
    "teaching_plan_link": "https://sys.ndhu.edu.tw/AA/CLASS/TeacherSubj/prt_tplan.aspx?no=111185018",
    "departments": [
        {
            "college": "管理學院::COLLEGE OF MANAGEMENT",
            "department": "國際企業學系::DEPARTMENT OF INTERNATIONAL BUSINESS"
        },
        {
            "college": "通識教育中心::GENERAL EDUCATION CENTER",
            "department": "通識教育中心學士班::BACHELOR"
        }
    ]
}