{
    "course_id": "GC__67600",
    "sql_id": "111159455",
    "course_name": "品牌創意與行銷",
    "english_course_name": "creative marketing and branding",
    "credits": "2/2",
    "teacher": [
        "林坤明"
    ],
    "classroom": [
        "管理學院-第一講堂B210",
        "管理學院-第一講堂B210"
    ],
    "class_time": [
        {
            "day": "三",
            "period": "5"
        },
        {
            "day": "三",
            "period": "6"
        }
    ],
    "syllabus_link": "https://sys.ndhu.edu.tw/AA/CLASS/SOutLine/OutLineForm.aspx?rid=111159455",
    "teaching_plan_link": "https://sys.ndhu.edu.tw/AA/CLASS/TeacherSubj/prt_tplan.aspx?no=111159455",
    "departments": [
        {
            "college": "通識教育中心::GENERAL EDUCATION CENTER",
            "department": "通識教育中心學士班::BACHELOR"
        }
    ]
}