{
    "course_id": "LF__33450",
    "sql_id": "111170920",
    "course_name": "生命科學前瞻",
    "english_course_name": "Frontiers in Life Science",
    "credits": "1/2",
    "teacher": [
        "陳季緯"
    ],
    "classroom": [
        "理工三館-階梯教室D104",
        "理工三館-階梯教室D104"
    ],
    "class_time": [
        {
            "day": "五",
            "period": "9"
        },
        {
            "day": "五",
            "period": "10"
        }
    ],
    "syllabus_link": "https://sys.ndhu.edu.tw/AA/CLASS/SOutLine/OutLineForm.aspx?rid=111170920",
    "teaching_plan_link": "https://sys.ndhu.edu.tw/AA/CLASS/TeacherSubj/prt_tplan.aspx?no=111170920",
    "departments": [
        {
            "college": "理工學院::COLLEGE OF SCIENCE AND ENGINEERING",
            "department": "生命科學系::DEPARTMENT OF LIFE SCIENCE"
        }
    ]
}